geocortex/reporting/client/__init__.py
geocortex/reporting/client/portal_utils.py
geocortex/reporting/client/reporting_service.py
geocortex_reporting_client-1.1.0.dist-info/LICENSE
geocortex_reporting_client-1.1.0.dist-info/METADATA
geocortex_reporting_client-1.1.0.dist-info/WHEEL
geocortex_reporting_client-1.1.0.dist-info/top_level.txt
geocortex_reporting_client-1.1.0.dist-info/RECORD
