Metadata-Version: 2.1
Name: geocortex-reporting-client
Version: 1.1.0
Summary: A Python client for running Geocortex Reporting jobs.
Home-page: https://github.com/geocortex/vertigis-reporting-client-py
Author: VertiGIS
Author-email: packages@geocortex.com
License: UNKNOWN
Platform: UNKNOWN
Classifier: Development Status :: 5 - Production/Stable
Classifier: Intended Audience :: Developers
Classifier: Intended Audience :: Science/Research
Classifier: License :: OSI Approved :: MIT License
Classifier: Operating System :: OS Independent
Classifier: Programming Language :: Python
Classifier: Programming Language :: Python :: 3
Classifier: Programming Language :: Python :: 3.6
Classifier: Programming Language :: Python :: 3.7
Classifier: Programming Language :: Python :: 3.8
Classifier: Programming Language :: Python :: 3.9
Classifier: Topic :: Scientific/Engineering :: GIS
Classifier: Topic :: Scientific/Engineering :: Information Analysis
Classifier: Topic :: Software Development :: Libraries :: Python Modules
Requires-Python: >=3.6.0
Requires-Dist: requests (<3,>=2.24.0)
Requires-Dist: websockets (<9,>=8.1)
Provides-Extra: dev
Requires-Dist: aiounittest (<2,>=1.4.0) ; extra == 'dev'
Requires-Dist: black (>=19.10b) ; extra == 'dev'
Requires-Dist: pylint (<3,>=2.5.3) ; extra == 'dev'
Requires-Dist: responses (<0.11,>=0.10.16) ; extra == 'dev'
